k9s/__init__.py
k9s/__version__.py
k9s/entrance.py
k9s/info.py
k9s/get/__init__.py
k9s/get/ziyuan_get.py
k9s/search/__init__.py
k9s/search/config.py
k9s/search/env.py
k9s/search/ingress.py
k9s/search/yaml_filter.py
k9s-1.0.56.dist-info/LICENSE
k9s-1.0.56.dist-info/METADATA
k9s-1.0.56.dist-info/WHEEL
k9s-1.0.56.dist-info/top_level.txt
k9s-1.0.56.dist-info/RECORD
