Metadata-Version: 2.1
Name: k9s
Version: 1.0.56
Summary: k8s operate
Author: chenxing
Author-email: chenxing@cjdropshipping.co
Classifier: Programming Language :: Python :: 3
Classifier: License :: OSI Approved :: MIT License
Classifier: Operating System :: OS Independent
Requires-Python: >=3
License-File: LICENSE
Requires-Dist: loguru >=0.6.0
Requires-Dist: cjops >=1.0.10
